{
  "personal": {
    "name": "堀下 栄太",
    "name_english": "Eita Horishita",
    "birth_date": "1985年",
    "current_position": "技術調査エキスパート",
    "current_company": "VALUENEX Japan",
    "location": "日本, 千葉県",
    "github": "https://github.com/sanskruthiya",
    "linkedin": "https://www.linkedin.com/in/eita-horishita-2b8a605a/"
  },
  "work_experience": [
    {
      "id": 1,
      "company": "VALUENEX株式会社",
      "position": "技術調査エキスパート",
      "department": "共創推進部",
      "period": "2018年10月 - 現在",
      "description": "文書情報のビッグデータ解析を活用した分析調査を実施。主に民間企業様の研究開発・知財・企画部門をクライアントとし、IP（知財情報）ランドスケープ分析、技術トレンドの分析、ホワイトスペースの探索、競合・協業候補企業の探索といった調査を担当。加えて、口コミや住民ワークショップのコメント等の解析による潜在的社会ニーズ調査の経験を有する。Pythonを使ったデータの前処理・ウェブスクレイピング・文書ベクトルの生成・次元削減等の実施と、QGIS/JavaScriptを使ったデータ可視化を得意とする。",
      "skills": ["技術動向調査", "計量書誌学", "IPランドスケープ", "自然言語処理", "データ可視化", "JavaScript", "Python"],
      "references": [
        {
          "title": "オンライン登壇：特許技術と研究論文の俯瞰解析でイノベーションの源泉を探す（日本語、概要のみ）",
          "type": "presentation",
          "url": "https://www.valuenex.com/jp/events-list/2024/innovation-through-data-analysis",
          "description": "「水素の生成・貯蔵・利活用に関する技術と研究の動向」といった3つのテーマについて、特許技術と学術研究の2つのデータソースを分析し、その手法と考察を解説したセミナー。"
        },
        {
          "title": "高精度3次元地図データにかかる技術動向調査（日本語のみ）",
          "type": "technical_report",
          "url": "https://www.meti.go.jp/meti_lib/report/2023FY/000616.pdf#page=430",
          "description": "経済産業省の「標準活用加速化支援事業」の一環でダイナミックマッププラットフォーム株式会社様からの受託にて実施した調査。報告書本編の参考資料部分にて分析調査を掲載。"
        }
      ]
    },
    {
      "id": 2,
      "company": "国際航業株式会社",
      "position": "シニアコンサルタント",
      "department": "海外本部 都市計画チーム",
      "period": "2014年11月 - 2018年8月",
      "description": "JICA受託による空間情報インフラ(GIS/NSDI)や都市インフラ管理にかかる戦略・政策・技術的なコンサルティング業務をウクライナ、ルワンダ、パプアニューギニアで実施したほか、JICA中小企業支援事業をスリランカ、東ティモールで実施。また、世界銀行受託による日本の都市計画や空間情報インフラに関するナレッジ調査の報告書執筆を担当。さらに日本の地方自治体における統合型GISの導入・運用にかかるコンサルティング業務を実施。",
      "skills": ["GIS", "都市計画", "国際開発", "政策コンサルティング", "プロジェクト管理"],
      "references": [
        {
          "title": "横浜開発ナレッジソースブック（英語のみ）",
          "type": "case_study",
          "url": "https://www.city.yokohama.lg.jp/business/kokusaikoryu/yport/material/pf_yport.files/0163_20190419.pdf",
          "description": "世界銀行受託による横浜の都市開発アプローチに関するケーススタディ"
        },
        {
          "title": "ルワンダ給水プロジェクト技術報告書（英語版）",
          "type": "technical_report",
          "url": "https://openjicareport.jica.go.jp/pdf/12364485_01.pdf",
          "description": "JICA技術協力プロジェクトにおけるGIS専門家としての技術移転報告書"
        }
      ]
    },
    {
      "id": 3,
      "company": "一般社団法人日本フェアトレード委員会",
      "position": "プロジェクトマネージャー",
      "department": "付加価値の高いコーヒー生産プロジェクト",
      "period": "2012年9月 - 2013年8月",
      "description": "スリランカの農村におけるソーシャルビジネスの企画・実行を統括管理。個別農家によって栽培されるコーヒーの品質向上を図りながら、コーヒーの輸出・販売のための会社の起業、キャンディ市内にて実店舗開設と従業員トレーニング、開店初期の運営までを行い、一連のビジネスモデル構築を実現。また、現地の政府機関の協力も得ながら、既存情報の少ない現地のコーヒー事情（歴史、品種、生産地、加工技術）について調査し、報告書に取りまとめた。",
      "skills": ["プロジェクト管理", "ソーシャルビジネス", "農業開発", "市場調査"],
      "references": [
        {
          "title": "スリランカコーヒー調査レポート（英語版）",
          "type": "research_paper",
          "url": "/deliverables/SriLankaCoffeeReport_20130919.pdf",
          "description": "スリランカ中央高地におけるコーヒー生産及び流通状況をまとめたレポート。"
        }
      ]
    },
    {
      "id": 4,
      "company": "JICA 青年海外協力隊",
      "position": "村落開発普及員",
      "department": "OVOP（一村一品）促進プロジェクト",
      "period": "2010年4月 - 2012年6月",
      "location": "スリランカ",
      "description": "一村一品（OVOP）促進プロジェクトの一環として、26ヶ月間の山村でのコミュニティ開発活動に従事。地域の特産品として、農業支援や手工芸品の開発と販路開拓の支援を生産者とともに実施した。",
      "skills": ["コミュニティ開発", "異文化コミュニケーション", "農村開発"]
    },
    {
      "id": 5,
      "company": "株式会社国際開発コンサルタンツ",
      "position": "都市計画コンサルタント",
      "department": "計画設計部まちづくりグループ",
      "period": "2008年4月 - 2010年3月",
      "description": "日本の地方自治体を対象とした都市計画専門のコンサルティング業務。既存の都市計画の改定、法定図書の作成代行、都市計画マスタープラン作成のための各種調査、土地区画整理事業の設計、市街地再開発事業の事業化計画、住民参加型まちづくりのワークショップ運営業務を担当。東京都23区、神奈川県横浜市、長野県佐久市、千葉県柏市、栃木県宇都宮市などで業務を実施。",
      "skills": ["都市計画", "GIS", "AutoCAD", "Illustrator", "住民参加", "法定文書作成"]
    }
  ],
  "education": [
    {
      "id": 1,
      "institution": "バーミンガム大学院",
      "degree": "国際開発学修士号（with Merit）",
      "location": "イギリス",
      "period": "2013年9月 - 2014年10月",
      "description": "開発途上国における空間情報システムと都市計画に焦点を当てた国際開発学を専攻。",
      "references": [
        {
          "title": "Dessertation: Application of the Geographic Information System (GIS) in developing countries",
          "type": "research_paper",
          "url": "/deliverables/Dissertation_Eita_Horishita.pdf",
          "description": "開発途上国でのGISの適用に関して、ザンビアでのインタビュー調査とケーススタディを交えて考察した修士論文。GISが組織改革の触媒として作用し得ることや、データ管理の課題が組織構造的なものであることを示唆。"
        }
      ]
    },
    {
      "id": 2,
      "institution": "千葉大学",
      "degree": "工学部都市環境システム学科 学士",
      "location": "日本",
      "period": "2004年4月 - 2008年3月",
      "description": "住民参加・コミュニティ開発に焦点を当てた都市環境システム工学を専攻。"
    }
  ],
  "skills": {
    "technical": ["QGIS", "ArcGIS", "MapLibre GL JS", "LeafletJS", "SvelteKit", "Python", "JavaScript", "MS Office"],
    "languages": [
      {
        "language": "日本語",
        "level": "母語"
      },
      {
        "language": "英語",
        "level": "ビジネスレベル(CEFR C1)",
        "certifications": ["TOEIC 935点 (2017年)", "IELTS 7.0 (2019年)"],
        "experience": "文書読解、メール交換、プレゼンテーション、報告書作成"
      },
      {
        "language": "シンハラ語",
        "level": "ビジネスレベル",
        "experience": "プレゼンテーション、通訳、交渉"
      }
    ],
    "specialties": [
      "GIS（地理情報システム）を用いた可視化・分析",
      "自然言語処理を用いた文書情報の分析",
      "計量書誌学的アプローチによるIP（知財）ランドスケープ分析",
      "開発途上国に向けた技術移転・戦略構築支援",
      "政府ODA関連事業における企画・提案・業務管理",
      "各種都市計画コンサルティング"
    ]
  },
  "certifications": [
    {
      "name": "普通自動車免許(第一種)",
      "date": "2006年9月"
    },
    {
      "name": "FASID PCM (計画立案、評価・モニタリング)",
      "date": "2016年6月"
    },
    {
      "name": "技術士補 (情報工学部門)",
      "date": "2017年11月"
    }
  ]
}
